brewblox_spark_api/__init__.py
brewblox_spark_api/__main__.py
brewblox_spark_api/blocks_api.py
brewblox_spark_api-0.3.0.dist-info/LICENSE
brewblox_spark_api-0.3.0.dist-info/WHEEL
brewblox_spark_api-0.3.0.dist-info/METADATA
brewblox_spark_api-0.3.0.dist-info/RECORD
