Metadata-Version: 2.1
Name: brewblox-spark-api
Version: 0.3.0
Summary: Client-side API for consuming Spark blocks
License: GPL-3.0
Author: BrewPi.bv
Author-email: development@brewpi.com
Requires-Python: >=3.9,<4
Classifier: License :: OSI Approved :: GNU General Public License v3 (GPLv3)
Classifier: Programming Language :: Python :: 3
Classifier: Programming Language :: Python :: 3.9
Classifier: Programming Language :: Python :: 3.10
Classifier: Programming Language :: Python :: 3.11
Requires-Dist: brewblox-service (>=1.0.0,<2.0.0)
